hofund.py
hofund-0.0.9.dist-info/METADATA
hofund-0.0.9.dist-info/WHEEL
hofund-0.0.9.dist-info/entry_points.txt
hofund-0.0.9.dist-info/top_level.txt
hofund-0.0.9.dist-info/RECORD
