Metadata-Version: 2.1
Name: hofund
Version: 0.0.9
Summary: allows user to search protos using stencil
Home-page: https://source.golabs.io/asgard/spikes/prototypes/hofund
Author: Ramey Girdhar
Author-email: ramey.girdhar@gojek.com
License: UNLICENSED
Platform: UNKNOWN
Classifier: Programming Language :: Python :: 3.9
Classifier: Operating System :: OS Independent
Requires-Python: >=3.9
Requires-Dist: aiohttp (==3.8.1)
Requires-Dist: aiodns (==3.0.0)
Requires-Dist: cchardet (==2.1.7)
Requires-Dist: pandas (==1.4.0)
Requires-Dist: setuptools (==58.1.0)
Requires-Dist: requests (==2.27.1)
Requires-Dist: protobuf (==3.19.4)
